README.txt
setup.cfg
setup.py
collective/__init__.py
collective.atimage.transformtoolbar.egg-info/PKG-INFO
collective.atimage.transformtoolbar.egg-info/SOURCES.txt
collective.atimage.transformtoolbar.egg-info/dependency_links.txt
collective.atimage.transformtoolbar.egg-info/entry_points.txt
collective.atimage.transformtoolbar.egg-info/namespace_packages.txt
collective.atimage.transformtoolbar.egg-info/not-zip-safe
collective.atimage.transformtoolbar.egg-info/requires.txt
collective.atimage.transformtoolbar.egg-info/top_level.txt
collective/atimage/__init__.py
collective/atimage/transformtoolbar/README.txt
collective/atimage/transformtoolbar/__init__.py
collective/atimage/transformtoolbar/configure.zcml
collective/atimage/transformtoolbar/interfaces.py
collective/atimage/transformtoolbar/Extensions/Install.py
collective/atimage/transformtoolbar/browser/__init__.py
collective/atimage/transformtoolbar/browser/configure.zcml
collective/atimage/transformtoolbar/browser/transform.py
collective/atimage/transformtoolbar/browser/viewlets.py
collective/atimage/transformtoolbar/browser/resources/transform-0.gif
collective/atimage/transformtoolbar/browser/resources/transform-1.gif
collective/atimage/transformtoolbar/browser/resources/transform-2.gif
collective/atimage/transformtoolbar/browser/resources/transform-3.gif
collective/atimage/transformtoolbar/browser/resources/transform-4.gif
collective/atimage/transformtoolbar/browser/resources/transformtoolbar.css
collective/atimage/transformtoolbar/browser/resources/transformtoolbar.js
collective/atimage/transformtoolbar/browser/templates/toolbar.pt
collective/atimage/transformtoolbar/profiles/default/browserlayer.xml
collective/atimage/transformtoolbar/profiles/default/cssregistry.xml
collective/atimage/transformtoolbar/profiles/default/jsregistry.xml
collective/atimage/transformtoolbar/profiles/default/viewlets.xml
collective/atimage/transformtoolbar/profiles/default/types/Image.xml
collective/atimage/transformtoolbar/profiles/uninstall/types/Image.xml
collective/atimage/transformtoolbar/tests/__init__.py
collective/atimage/transformtoolbar/tests/base.py
collective/atimage/transformtoolbar/tests/test_doctest.py
collective/atimage/transformtoolbar/tests/samples/test_image.png
docs/AUTHORS.txt
docs/HISTORY.txt
docs/INSTALL.txt
docs/LICENSE.GPL
docs/LICENSE.txt