Metadata-Version: 1.0
Name: collective.atimage.transformtoolbar
Version: 1.2.3
Summary: 'Transforms' toolbar in Image and News Item to perform image transformations
Home-page: http://svn.plone.org/svn/collective/collective.atimage.transformtoolbar
Author: marcosfromero
Author-email: marcos.romero {at} inter-cultura {dot} com
License: GPL
Platform: UNKNOWN
Classifier: Programming Language :: Python
Classifier: Framework :: Plone
